fake_spectra/__init__.py
fake_spectra/_spectra_priv.cpython-311-darwin.so
fake_spectra/abstractsnapshot.py
fake_spectra/atom.dat
fake_spectra/emission.py
fake_spectra/fluxstatistics.py
fake_spectra/gas_properties.py
fake_spectra/get_python_libdir.py
fake_spectra/griddedspectra.py
fake_spectra/haloassigned_spectra.py
fake_spectra/halocat.py
fake_spectra/halospectra.py
fake_spectra/lab.py
fake_spectra/line_data.py
fake_spectra/plot_spectra.py
fake_spectra/randspectra.py
fake_spectra/rate_network.py
fake_spectra/rate_network_plot.py
fake_spectra/ratenetworkspectra.py
fake_spectra/spec_utils.py
fake_spectra/spectra.py
fake_spectra/subfindhdf.py
fake_spectra/tempdens.py
fake_spectra/unitsystem.py
fake_spectra/voigtfit.py
fake_spectra/cloudy_tables/convert_cloudy.py
fake_spectra/cloudy_tables/make_cloudy_input.py
fake_spectra/cloudy_tables/make_dens_plot.py
fake_spectra/cloudy_tables/photocs.py
fake_spectra/cloudy_tables/test_cloudy.py
fake_spectra/cloudy_tables/ion_out_no_atten/cloudy_table.npz
fake_spectra/cloudy_tables/ion_out_photo_atten/cloudy_table.npz
fake_spectra/data/TREECOOL
fake_spectra/data/TREECOOL_ep_2018p
fake_spectra/tests/example_civ_tau.npz
fake_spectra/tests/test_rate_network.py
fake_spectra/tests/test_spectra.py
fake_spectra/tests/test_statistics.py
fake_spectra-2.2.3.dist-info/LICENSE
fake_spectra-2.2.3.dist-info/METADATA
fake_spectra-2.2.3.dist-info/WHEEL
fake_spectra-2.2.3.dist-info/top_level.txt
fake_spectra-2.2.3.dist-info/RECORD
