Metadata-Version: 2.1
Name: fake-spectra
Version: 2.2.3
Summary: Analysis tools for generating artificial spectra from simulations.
Home-page: http://github.com/sbird/fake_spectra
Author: Simeon Bird
Author-email: spb@ucr.edu
Classifier: Development Status :: 4 - Beta
Classifier: Intended Audience :: Developers
Classifier: Intended Audience :: Science/Research
Classifier: License :: OSI Approved :: MIT License
Classifier: Programming Language :: Python :: 3
Classifier: Topic :: Scientific/Engineering :: Astronomy
Classifier: Topic :: Scientific/Engineering :: Visualization
Requires: numpy
Requires: h5py
Requires: scipy
License-File: LICENSE
